{
  "name": "bower-search-result",
  "_cacheHeaders": {
    "ETag": "\"32a2042-22a7b-5376eb2875ef4\"",
    "Last-Modified": "Tue, 12 Jul 2016 11:37:44 GMT",
    "Content-Length": "141947",
    "Content-Type": "image/jpeg"
  },
  "_release": "e-tag:32a2042-2",
  "main": "index.jpg",
  "_source": "http://media02.hongkiat.com/bower-package-manager/bower-search-result.jpg",
  "_target": "*",
  "_originalSource": "http://media02.hongkiat.com/bower-package-manager/bower-search-result.jpg",
  "_direct": true
}